pytensils/__init__.py
pytensils/config.py
pytensils/errors.py
pytensils/logging.py
pytensils/profiler.py
pytensils/utils.py
pytensils-1.4.0.dist-info/licenses/LICENSE
pytensils-1.4.0.dist-info/METADATA
pytensils-1.4.0.dist-info/WHEEL
pytensils-1.4.0.dist-info/top_level.txt
pytensils-1.4.0.dist-info/RECORD
