Metadata-Version: 2.4
Name: pytensils
Version: 1.4.0
Summary: A Python package that provides general utility functions for managing configuration, user-logging, directories and data-types as well as a basic run-time profiler.
Home-page: https://github.com/thomaseleff/pytensils
Author: Tom Eleff
Project-URL: Issues, https://github.com/thomaseleff/pytensils/issues
Project-URL: Releases, https://github.com/thomaseleff/pytensils/releases
Classifier: Development Status :: 4 - Beta
Classifier: Topic :: Utilities
Classifier: License :: OSI Approved :: MIT License
Classifier: Programming Language :: Python :: 3.8
Classifier: Programming Language :: Python :: 3.9
Classifier: Programming Language :: Python :: 3.10
Classifier: Programming Language :: Python :: 3.11
Classifier: Programming Language :: Python :: 3.12
Requires-Python: >=3.7.1
License-File: LICENSE
Requires-Dist: pandas>=1.3.5
Requires-Dist: tabulate==0.9.0
Requires-Dist: typing-extensions>=4.3.0
Dynamic: license-file
